SASO_mastertrust/__init__.py
SASO_mastertrust/mastertrust.py
SASOupstox/__init__.py
SASOupstox/upstox.py
SASOzebu/__init__.py
SASOzebu/zebu.py
UpstoxWithoutAPI/__init__.py
UpstoxWithoutAPI/upstox.py
aliceblue_fetch_data/__init__.py
aliceblue_fetch_data/alice.py
copytrading_upstox/__init__.py
copytrading_upstox/upstox.py
copytrading_upstox_withoutapi/__init__.py
copytrading_upstox_withoutapi/upstox.py
fyers_withoutapi/__init__.py
fyers_withoutapi/fyers.py
upstox_withoutapi/__init__.py
upstox_withoutapi/upstox.py
zerodha_without_api/__init__.py
zerodha_without_api/zerodha.py
SASOzebu-0.0.1.dist-info/LICENSE
SASOzebu-0.0.1.dist-info/METADATA
SASOzebu-0.0.1.dist-info/WHEEL
SASOzebu-0.0.1.dist-info/top_level.txt
SASOzebu-0.0.1.dist-info/RECORD
