Metadata-Version: 2.1
Name: SASOzebu
Version: 0.0.1
Summary: ZEBU free run
Author: Gourav
Author-email: kgourav@combiz.org
Keywords: ZEBU,ZEBU api use
Classifier: Development Status :: 1 - Planning
Classifier: Intended Audience :: Developers
Classifier: Programming Language :: Python :: 3
Classifier: Operating System :: Unix
Classifier: Operating System :: MacOS :: MacOS X
Classifier: Operating System :: Microsoft :: Windows
License-File: LICENSE
Requires-Dist: requests
